kaiko/__init__.py
kaiko/__main__.py
kaiko/_version.py
kaiko/beatanalyzer.py
kaiko/beatbar.py
kaiko/beatcmd.py
kaiko/beatmap.py
kaiko/beatmenu.py
kaiko/beatsheet.py
kaiko/beatshell.py
kaiko/biparser.py
kaiko/cfg.py
kaiko/datanodes.py
kaiko/kerminal.py
kaiko/tui.py
kaiko/beats/__init__.py
kaiko/beats/beatanalyzer.py
kaiko/beats/beatbar.py
kaiko/beats/beatmaps.py
kaiko/beats/beatpatterns.py
kaiko/beats/beatsheets.py
kaiko/beats/beatshell.py
kaiko/beats/beatwidgets.py
kaiko/devices/__init__.py
kaiko/devices/audios.py
kaiko/devices/clocks.py
kaiko/devices/engines.py
kaiko/devices/loggers.py
kaiko/devices/terminals.py
kaiko/main/__init__.py
kaiko/main/beatshell.py
kaiko/main/bgm.py
kaiko/main/devices.py
kaiko/main/files.py
kaiko/main/launcher.py
kaiko/main/loggers.py
kaiko/main/menu.py
kaiko/main/play.py
kaiko/main/profiles.py
kaiko/main/settings.py
kaiko/main/songs.py
kaiko/menu/__init__.py
kaiko/menu/beatmenu.py
kaiko/menu/devices.py
kaiko/menu/profiles.py
kaiko/menu/songs.py
kaiko/samples/disk.wav
kaiko/samples/incr.wav
kaiko/samples/loud.wav
kaiko/samples/rock.wav
kaiko/samples/soft.wav
kaiko/tui/__init__.py
kaiko/tui/beatbars.py
kaiko/tui/inputs.py
kaiko/tui/sheditors.py
kaiko/tui/textboxes.py
kaiko/tui/widgets.py
kaiko/utils/__init__.py
kaiko/utils/biparsers.py
kaiko/utils/commands.py
kaiko/utils/config.py
kaiko/utils/datanodes.py
kaiko/utils/engines.py
kaiko/utils/markups.py
kaiko/utils/parsec.py
kaiko/utils/providers.py
kaiko/utils/serializers.py
kaiko/utils/wcbuffers.py
K_AIKO-0.5.2.dist-info/LICENSE
K_AIKO-0.5.2.dist-info/METADATA
K_AIKO-0.5.2.dist-info/WHEEL
K_AIKO-0.5.2.dist-info/entry_points.txt
K_AIKO-0.5.2.dist-info/top_level.txt
K_AIKO-0.5.2.dist-info/RECORD
