Metadata-Version: 2.1
Name: K-AIKO
Version: 0.5.2
Summary: A sound-controlled terminal-based rhythm game
Home-page: https://github.com/worldmaker18349276/K-AIKO
Author: worldmaker18349276
Author-email: worldmaker18349276@gmail.com
License: MIT
Project-URL: Issue Tracker, https://github.com/worldmaker18349276/K-AIKO/issues
Keywords: sound-controlled,terminal-based,rhythm game
Platform: UNKNOWN
Classifier: Development Status :: 2 - Pre-Alpha
Classifier: Intended Audience :: End Users/Desktop
Classifier: Topic :: Games/Entertainment
Classifier: License :: OSI Approved :: MIT License
Classifier: Environment :: Console
Classifier: Programming Language :: Python :: 3.9
Requires-Python: >=3.9, <4
License-File: LICENSE
Requires-Dist: numpy
Requires-Dist: scipy
Requires-Dist: numexpr
Requires-Dist: audioread
Requires-Dist: pyaudio
Requires-Dist: wcwidth
